Workbook

Sheet RETAIL SALES DATA.
A1: Order_ID | B1: Customer_Name | C1: Product_Name | D1: Product_Category | E1: Region | F1: Sales_Quantity | G1: Unit_Price | H1: Sales_Amount | I1: Cost | J1: Profit | K1: Order_Date | L1: Delivery_Date | M1: Employee_Name | N1: Customer_Rating | O1: Login_Time | P1: Working_Hours | Q1: Orders | R1: HIGH VALUE/LOW | S1: P/L | T1: CUSTOMER NAME | U1: PRUDUCT | V1: YEAR | W1: MONTH | X1: DAY | Y1: MONTH2 | Z1: DELIVERY DATE
A2: ORD0001 | B2: Michael Winters | C2: Pen | D2: Office Supplies | E2: South | F2: 4 | G2: 1578.68 | H2: 6314.72 | I2: 4409.14 | J2: 1905.58 | K2: 45913 | L2: 45922 | M2: Rahul | N2: 5 | O2: 10:12:00 | P2: 8.9 | Q2: =RIGHT(A2,"4") -> 0001 | R2: =IF('RETAIL SALES DATA.'!H2>AVERAGE('RETAIL SALES DATA.'!H2:H1001),"HIGHEST VALUE","LOWEST VALUE") -> LOWEST VALUE | S2: =IF(J2>0,"Profit","Loss") -> Profit | T2: =PROPER(B2) -> Michael Winters | U2: =PROPER(C2) -> Pen | V2: =YEAR(K2) -> 2025 | W2: =MONTH(L2) -> 9 | X2: =DAY(K2) -> 13 | Y2: =TEXT(K2,"MMM") -> Sep | Z2: =L2-K2 -> 9
A3: ORD0002 | B3: James Olson | C3: Pen | D3: Office Supplies | E3: North | F3: 18 | G3: 1427.85 | H3: 25701.3 | I3: 15663.81 | J3: 10037.49 | K3: 46023 | L3: 46026 | M3: Megha | N3: 1 | O3: 08:15:00 | P3: 8.6 | Q3: =RIGHT(A3,"4") -> 0002 | R3: =IF('RETAIL SALES DATA.'!H3>AVERAGE('RETAIL SALES DATA.'!H3:H1002),"HIGHEST VALUE","LOWEST VALUE") -> LOWEST VALUE | S3: =IF(J3>0,"Profit","Loss") -> Profit | T3: =PROPER(B3) -> James Olson | U3: =PROPER(C3) -> Pen | V3: =YEAR(K3) -> 2026 | W3: =MONTH(L3) -> 1 | X3: =DAY(K3) -> 1 | Y3: =TEXT(K3,"MMM") -> Jan | Z3: =L3-K3 -> 3
A4: ORD0003 | B4: Brittney Simmons | C4: Desk | D4: Furniture | E4: West | F4: 18 | G4: 3667.53 | H4: 66015.54 | I4: 41337.25 | J4: 24678.29 | K4: 46152 | L4: 46161 | M4: Arun | N4: 5 | O4: 11:33:00 | P4: 7.3 | Q4: =RIGHT(A4,"4") -> 0003 | R4: =IF('RETAIL SALES DATA.'!H4>AVERAGE('RETAIL SALES DATA.'!H4:H1003),"HIGHEST VALUE","LOWEST VALUE") -> HIGHEST VALUE | S4: =IF(J4>0,"Profit","Loss") -> Profit | T4: =PROPER(B4) -> Brittney Simmons | U4: =PROPER(C4) -> Desk | V4: =YEAR(K4) -> 2026 | W4: =MONTH(L4) -> 5 | X4: =DAY(K4) -> 10 | Y4: =TEXT(K4,"MMM") -> May | Z4: =L4-K4 -> 9
A5: ORD0004 | B5: Courtney Park | C5: Marker | D5: Office Supplies | E5: North | F5: 1 | G5: 3550.31 | H5: 3550.31 | I5: 2061.79 | J5: 1488.52 | K5: 45483 | L5: 45491 | M5: Vivek | N5: 4 | O5: 11:19:00 | P5: 6.5 | Q5: =RIGHT(A5,"4") -> 0004 | R5: =IF('RETAIL SALES DATA.'!H5>AVERAGE('RETAIL SALES DATA.'!H5:H1004),"HIGHEST VALUE","LOWEST VALUE") -> LOWEST VALUE | S5: =IF(J5>0,"Profit","Loss") -> Profit | T5: =PROPER(B5) -> Courtney Park | U5: =PROPER(C5) -> Marker | V5: =YEAR(K5) -> 2024 | W5: =MONTH(L5) -> 7 | X5: =DAY(K5) -> 10 | Y5: =TEXT(K5,"MMM") -> Jul | Z5: =L5-K5 -> 8
A6: ORD0005 | B6: Chloe Villa | C6: Laptop | D6: Electronics | E6: East | F6: 13 | G6: 1838.36 | H6: 23898.68 | I6: 17283.83 | J6: 6614.85 | K6: 46052 | L6: 46062 | M6: Diya | N6: 1 | O6: 10:02:00 | P6: 8.7 | Q6: =RIGHT(A6,"4") -> 0005 | R6: =IF('RETAIL SALES DATA.'!H6>AVERAGE('RETAIL SALES DATA.'!H6:H1005),"HIGHEST VALUE","LOWEST VALUE") -> LOWEST VALUE | S6: =IF(J6>0,"Profit","Loss") -> Profit | T6: =PROPER(B6) -> Chloe Villa | U6: =PROPER(C6) -> Laptop | V6: =YEAR(K6) -> 2026 | W6: =MONTH(L6) -> 2 | X6: =DAY(K6) -> 30 | Y6: =TEXT(K6,"MMM") -> Jan | Z6: =L6-K6 -> 10
A7: ORD0006 | B7: Erin Ross | C7: Mouse | D7: Electronics | E7: West | F7: 1 | G7: 4093.77 | H7: 4093.77 | I7: 2721.22 | J7: 1372.55 | K7: 45502 | L7: 45505 | M7: Fathima | N7: 1 | O7: 09:28:00 | P7: 8.6 | Q7: =RIGHT(A7,"4") -> 0006 | R7: =IF('RETAIL SALES DATA.'!H7>AVERAGE('RETAIL SALES DATA.'!H7:H1006),"HIGHEST VALUE","LOWEST VALUE") -> LOWEST VALUE | S7: =IF(J7>0,"Profit","Loss") -> Profit | T7: =PROPER(B7) -> Erin Ross | U7: =PROPER(C7) -> Mouse | V7: =YEAR(K7) -> 2024 | W7: =MONTH(L7) -> 8 | X7: =DAY(K7) -> 29 | Y7: =TEXT(K7,"MMM") -> Jul | Z7: =L7-K7 -> 3
A8: ORD0007 | B8: Ryan Brown | C8: Laptop | D8: Electronics | E8: West | F8: 17 | G8: 2540.86 | H8: 43194.62 | I8: 22584.56 | J8: 20610.06 | K8: 45494 | L8: 45498 | M8: Rahul | N8: 1 | O8: 08:18:00 | P8: 8.9 | Q8: =RIGHT(A8,"4") -> 0007 | R8: =IF('RETAIL SALES DATA.'!H8>AVERAGE('RETAIL SALES DATA.'!H8:H1007),"HIGHEST VALUE","LOWEST VALUE") -> HIGHEST VALUE | S8: =IF(J8>0,"Profit","Loss") -> Profit | T8: =PROPER(B8) -> Ryan Brown | U8: =PROPER(C8) -> Laptop | V8: =YEAR(K8) -> 2024 | W8: =MONTH(L8) -> 7 | X8: =DAY(K8) -> 21 | Y8: =TEXT(K8,"MMM") -> Jul | Z8: =L8-K8 -> 4
A9: ORD0008 | B9: Keith Winters | C9: Notebook | D9: Office Supplies | E9: East | F9: 12 | G9: 4957.92 | H9: 59495.04 | I9: 49409.66 | J9: 10085.38 | K9: 46147 | L9: 46150 | M9: Sneha | N9: 2 | O9: 09:04:00 | P9: 8 | Q9: =RIGHT(A9,"4") -> 0008 | R9: =IF('RETAIL SALES DATA.'!H9>AVERAGE('RETAIL SALES DATA.'!H9:H1008),"HIGHEST VALUE","LOWEST VALUE") -> HIGHEST VALUE | S9: =IF(J9>0,"Profit","Loss") -> Profit | T9: =PROPER(B9) -> Keith Winters | U9: =PROPER(C9) -> Notebook | V9: =YEAR(K9) -> 2026 | W9: =MONTH(L9) -> 5 | X9: =DAY(K9) -> 5 | Y9: =TEXT(K9,"MMM") -> May | Z9: =L9-K9 -> 3
A10: ORD0009 | B10: Richard Payne | C10: Table | D10: Furniture | E10: East | F10: 2 | G10: 3280.82 | H10: 6561.64 | I10: 5871.1 | J10: 690.54 | K10: 45607 | L10: 45610 | M10: Vivek | N10: 1 | O10: 11:17:00 | P10: 6.6 | Q10: =RIGHT(A10,"4") -> 0009 | R10: =IF('RETAIL SALES DATA.'!H10>AVERAGE('RETAIL SALES DATA.'!H10:H1009),"HIGHEST VALUE","LOWEST VALUE") -> LOWEST VALUE | S10: =IF(J10>0,"Profit","Loss") -> Profit | T10: =PROPER(B10) -> Richard Payne | U10: =PROPER(C10) -> Table | V10: =YEAR(K10) -> 2024 | W10: =MONTH(L10) -> 11 | X10: =DAY(K10) -> 11 | Y10: =TEXT(K10,"MMM") -> Nov | Z10: =L10-K10 -> 3
A11: ORD0010 | B11: Cory Roberson | C11: Pen | D11: Office Supplies | E11: North | F11: 14 | G11: 1988.47 | H11: 27838.58 | I11: 19080.73 | J11: 8757.85 | K11: 45712 | L11: 45716 | M11: Rahul | N11: 2 | O11: 11:14:00 | P11: 9.4 | Q11: =RIGHT(A11,"4") -> 0010 | R11: =IF('RETAIL SALES DATA.'!H11>AVERAGE('RETAIL SALES DATA.'!H11:H1010),"HIGHEST VALUE","LOWEST VALUE") -> HIGHEST VALUE | S11: =IF(J11>0,"Profit","Loss") -> Profit | T11: =PROPER(B11) -> Cory Roberson | U11: =PROPER(C11) -> Pen | V11: =YEAR(K11) -> 2025 | W11: =MONTH(L11) -> 2 | X11: =DAY(K11) -> 24 | Y11: =TEXT(K11,"MMM") -> Feb | Z11: =L11-K11 -> 4 | AB11: MONTH | AC11: 2025 | AD11: 2024 | AE11: 2026
A12: ORD0011 | B12: Amanda Cox | C12: Desk | D12: Furniture | E12: North | F12: 15 | G12: 991.66 | H12: 14874.9 | I12: 11249.49 | J12: 3625.41 | K12: 45628 | L12: 45634 | M12: Akhil | N12: 5 | O12: 11:14:00 | P12: 9.5 | Q12: =RIGHT(A12,"4") -> 0011 | R12: =IF('RETAIL SALES DATA.'!H12>AVERAGE('RETAIL SALES DATA.'!H12:H1011),"HIGHEST VALUE","LOWEST VALUE") -> LOWEST VALUE | S12: =IF(J12>0,"Profit","Loss") -> Profit | T12: =PROPER(B12) -> Amanda Cox | U12: =PROPER(C12) -> Desk | V12: =YEAR(K12) -> 2024 | W12: =MONTH(L12) -> 12 | X12: =DAY(K12) -> 2 | Y12: =TEXT(K12,"MMM") -> Dec | Z12: =L12-K12 -> 6 | AB12: Jan | AC12: =SUMIFS($H$2:$H$1001,$Y$2:$Y$1001,AB12,$V$2:$V$1001,V986) -> 931394.12 | AD12: =SUMIFS($H$2:$H$1001,$Y$2:$Y$1001,AB12,$V$2:$V$1001,V990) -> 0 | AE12: =SUMIFS($H$2:$H$1001,$Y$2:$Y$1001,AB12,$V$2:$V$1001,V3) -> 1122389.7
A13: ORD0012 | B13: Joseph Allison | C13: Chair | D13: Furniture | E13: South | F13: 12 | G13: 4247.3 | H13: 50967.6 | I13: 39899.98 | J13: 11067.62 | K13: 45786 | L13: 45795 | M13: Sneha | N13: 3 | O13: 11:34:00 | P13: 6.8 | Q13: =RIGHT(A13,"4") -> 0012 | R13: =IF('RETAIL SALES DATA.'!H13>AVERAGE('RETAIL SALES DATA.'!H13:H1012),"HIGHEST VALUE","LOWEST VALUE") -> HIGHEST VALUE | S13: =IF(J13>0,"Profit","Loss") -> Profit | T13: =PROPER(B13) -> Joseph Allison | U13: =PROPER(C13) -> Chair | V13: =YEAR(K13) -> 2025 | W13: =MONTH(L13) -> 5 | X13: =DAY(K13) -> 9 | Y13: =TEXT(K13,"MMM") -> May | Z13: =L13-K13 -> 9 | AB13: Feb | AC13: =SUMIFS($H$2:$H$1001,$Y$2:$Y$1001,AB13,$V$2:$V$1001,V987) -> 1188601.5 | AD13: =SUMIFS($H$2:$H$1001,$Y$2:$Y$1001,AB13,$V$2:$V$1001,V991) -> 0 | AE13: =SUMIFS($H$2:$H$1001,$Y$2:$Y$1001,AB13,$V$2:$V$1001,V4) -> 855184.88
A14: ORD0013 | B14: Sarah Hernandez | C14: Desk | D14: Furniture | E14: East | F14: 10 | G14: 761.02 | H14: 7610.2 | I14: 4990.85 | J14: 2619.35 | K14: 45812 | L14: 45817 | M14: Rahul | N14: 1 | O14: 09:38:00 | P14: 8.1 | Q14: =RIGHT(A14,"4") -> 0013 | R14: =IF('RETAIL SALES DATA.'!H14>AVERAGE('RETAIL SALES DATA.'!H14:H1013),"HIGHEST VALUE","LOWEST VALUE") -> LOWEST VALUE | S14: =IF(J14>0,"Profit","Loss") -> Profit | T14: =PROPER(B14) -> Sarah Hernandez | U14: =PROPER(C14) -> Desk | V14: =YEAR(K14) -> 2025 | W14: =MONTH(L14) -> 6 | X14: =DAY(K14) -> 4 | Y14: =TEXT(K14,"MMM") -> Jun | Z14: =L14-K14 -> 5 | AB14: Mar | AC14: =SUMIFS($H$2:$H$1001,$Y$2:$Y$1001,AB14,$V$2:$V$1001,V988) -> 1343369.7 | AD14: =SUMIFS($H$2:$H$1001,$Y$2:$Y$1001,AB14,$V$2:$V$1001,V992) -> 1343369.7 | AE14: =SUMIFS($H$2:$H$1001,$Y$2:$Y$1001,AB14,$V$2:$V$1001,V5) -> 0 | AI14: YEAR
A15: ORD0014 | B15: John Dixon | C15: Laptop | D15: Electronics | E15: West | F15: 4 | G15: 2151.7 | H15: 8606.8 | I15: 7408.45 | J15: 1198.35 | K15: 45747 | L15: 45754 | M15: Vivek | N15: 1 | O15: 10:16:00 | P15: 7.5 | Q15: =RIGHT(A15,"4") -> 0014 | R15: =IF('RETAIL SALES DATA.'!H15>AVERAGE('RETAIL SALES DATA.'!H15:H1014),"HIGHEST VALUE","LOWEST VALUE") -> LOWEST VALUE | S15: =IF(J15>0,"Profit","Loss") -> Profit | T15: =PROPER(B15) -> John Dixon | U15: =PROPER(C15) -> Laptop | V15: =YEAR(K15) -> 2025 | W15: =MONTH(L15) -> 4 | X15: =DAY(K15) -> 31 | Y15: =TEXT(K15,"MMM") -> Mar | Z15: =L15-K15 -> 7 | AB15: Apr | AC15: =SUMIFS($H$2:$H$1001,$Y$2:$Y$1001,AB15,$V$2:$V$1001,V989) -> 898947.59 | AD15: =SUMIFS($H$2:$H$1001,$Y$2:$Y$1001,AB15,$V$2:$V$1001,V993) -> 1380237 | AE15: =SUMIFS($H$2:$H$1001,$Y$2:$Y$1001,AB15,$V$2:$V$1001,V6) -> 898947.59 | AI15: 2024 | AJ15: =SUMIF($V$2:$V$1001,AI15,$H$2:$H$1001) -> 8340960.3
A16: ORD0015 | B16: Javier Cole | C16: Table | D16: Furniture | E16: South | F16: 1 | G16: 1909.53 | H16: 1909.53 | I16: 1574.6 | J16: 334.93 | K16: 45765 | L16: 45766 | M16: Megha | N16: 4 | O16: 09:13:00 | P16: 8.5 | Q16: =RIGHT(A16,"4") -> 0015 | R16: =IF('RETAIL SALES DATA.'!H16>AVERAGE('RETAIL SALES DATA.'!H16:H1015),"HIGHEST VALUE","LOWEST VALUE") -> LOWEST VALUE | S16: =IF(J16>0,"Profit","Loss") -> Profit | T16: =PROPER(B16) -> Javier Cole | U16: =PROPER(C16) -> Table | V16: =YEAR(K16) -> 2025 | W16: =MONTH(L16) -> 4 | X16: =DAY(K16) -> 18 | Y16: =TEXT(K16,"MMM") -> Apr | Z16: =L16-K16 -> 1 | AB16: May | AC16: =SUMIFS($H$2:$H$1001,$Y$2:$Y$1001,AB16,$V$2:$V$1001,V990) -> 530012.66 | AD16: =SUMIFS($H$2:$H$1001,$Y$2:$Y$1001,AB16,$V$2:$V$1001,V994) -> 1003309.7 | AE16: =SUMIFS($H$2:$H$1001,$Y$2:$Y$1001,AB16,$V$2:$V$1001,V7) -> 530012.66 | AI16: 2025 | AJ16: =SUMIF($V$2:$V$1001,AI16,$H$2:$H$1001) -> 13413606
A17: ORD0016 | B17: Nathan Kline | C17: Laptop | D17: Electronics | E17: West | F17: 13 | G17: 4687.55 | H17: 60938.15 | I17: 46078.82 | J17: 14859.33 | K17: 45880 | L17: 45883 | M17: Megha | N17: 4 | O17: 10:56:00 | P17: 7.1 | Q17: =RIGHT(A17,"4") -> 0016 | R17: =IF('RETAIL SALES DATA.'!H17>AVERAGE('RETAIL SALES DATA.'!H17:H1016),"HIGHEST VALUE","LOWEST VALUE") -> HIGHEST VALUE | S17: =IF(J17>0,"Profit","Loss") -> Profit | T17: =PROPER(B17) -> Nathan Kline | U17: =PROPER(C17) -> Laptop | V17: =YEAR(K17) -> 2025 | W17: =MONTH(L17) -> 8 | X17: =DAY(K17) -> 11 | Y17: =TEXT(K17,"MMM") -> Aug | Z17: =L17-K17 -> 3 | AB17: Jun | AC17: =SUMIFS($H$2:$H$1001,$Y$2:$Y$1001,AB17,$V$2:$V$1001,V991) -> 1180005.8 | AD17: =SUMIFS($H$2:$H$1001,$Y$2:$Y$1001,AB17,$V$2:$V$1001,V995) -> 0 | AE17: =SUMIFS($H$2:$H$1001,$Y$2:$Y$1001,AB17,$V$2:$V$1001,V8) -> 1180005.8 | AI17: 2026 | AJ17: =SUMIF($V$2:$V$1001,AI17,$H$2:$H$1001) -> 4716577.1
A18: ORD0017 | B18: Miss Christina Taylor | C18: Cupboard | D18: Furniture | E18: West | F18: 17 | G18: 4690.31 | H18: 79735.27 | I18: 45830.53 | J18: 33904.74 | K18: 46152 | L18: 46153 | M18: Fathima | N18: 5 | O18: 10:58:00 | P18: 7.7 | Q18: =RIGHT(A18,"4") -> 0017 | R18: =IF('RETAIL SALES DATA.'!H18>AVERAGE('RETAIL SALES DATA.'!H18:H1017),"HIGHEST VALUE","LOWEST VALUE") -> HIGHEST VALUE | S18: =IF(J18>0,"Profit","Loss") -> Profit | T18: =PROPER(B18) -> Miss Christina Taylor | U18: =PROPER(C18) -> Cupboard | V18: =YEAR(K18) -> 2026 | W18: =MONTH(L18) -> 5 | X18: =DAY(K18) -> 10 | Y18: =TEXT(K18,"MMM") -> May | Z18: =L18-K18 -> 1 | AB18: Jul | AC18: =SUMIFS($H$2:$H$1001,$Y$2:$Y$1001,AB18,$V$2:$V$1001,V992) -> 1051466.1 | AD18: =SUMIFS($H$2:$H$1001,$Y$2:$Y$1001,AB18,$V$2:$V$1001,V996) -> 1051466.1 | AE18: =SUMIFS($H$2:$H$1001,$Y$2:$Y$1001,AB18,$V$2:$V$1001,V9) -> 0
A19: ORD0018 | B19: Martin Morton | C19: Laptop | D19: Electronics | E19: North | F19: 19 | G19: 4107.4 | H19: 78040.6 | I19: 57454.36 | J19: 20586.24 | K19: 45814 | L19: 45817 | M19: Fathima | N19: 3 | O19: 09:20:00 | P19: 6 | Q19: =RIGHT(A19,"4") -> 0018 | R19: =IF('RETAIL SALES DATA.'!H19>AVERAGE('RETAIL SALES DATA.'!H19:H1018),"HIGHEST VALUE","LOWEST VALUE") -> HIGHEST VALUE | S19: =IF(J19>0,"Profit","Loss") -> Profit | T19: =PROPER(B19) -> Martin Morton | U19: =PROPER(C19) -> Laptop | V19: =YEAR(K19) -> 2025 | W19: =MONTH(L19) -> 6 | X19: =DAY(K19) -> 6 | Y19: =TEXT(K19,"MMM") -> Jun | Z19: =L19-K19 -> 3 | AB19: Aug | AC19: =SUMIFS($H$2:$H$1001,$Y$2:$Y$1001,AB19,$V$2:$V$1001,V993) -> 1122773.1 | AD19: =SUMIFS($H$2:$H$1001,$Y$2:$Y$1001,AB19,$V$2:$V$1001,V997) -> 1122773.1 | AE19: =SUMIFS($H$2:$H$1001,$Y$2:$Y$1001,AB19,$V$2:$V$1001,V10) -> 1435955.9
A20: ORD0019 | B20: Adam Mullins | C20: Printer | D20: Office Supplies | E20: South | F20: 8 | G20: 1560.78 | H20: 12486.24 | I20: 9150.61 | J20: 3335.63 | K20: 46104 | L20: 46112 | M20: Fathima | N20: 3 | O20: 08:53:00 | P20: 7 | Q20: =RIGHT(A20,"4") -> 0019 | R20: =IF('RETAIL SALES DATA.'!H20>AVERAGE('RETAIL SALES DATA.'!H20:H1019),"HIGHEST VALUE","LOWEST VALUE") -> LOWEST VALUE | S20: =IF(J20>0,"Profit","Loss") -> Profit | T20: =PROPER(B20) -> Adam Mullins | U20: =PROPER(C20) -> Printer | V20: =YEAR(K20) -> 2026 | W20: =MONTH(L20) -> 3 | X20: =DAY(K20) -> 23 | Y20: =TEXT(K20,"MMM") -> Mar | Z20: =L20-K20 -> 8 | AB20: Sep | AC20: =SUMIFS($H$2:$H$1001,$Y$2:$Y$1001,AB20,$V$2:$V$1001,V994) -> 1045399.3 | AD20: =SUMIFS($H$2:$H$1001,$Y$2:$Y$1001,AB20,$V$2:$V$1001,V998) -> 1045399.3 | AE20: =SUMIFS($H$2:$H$1001,$Y$2:$Y$1001,AB20,$V$2:$V$1001,V11) -> 1045399.3
A21: ORD0020 | B21: Sean Rodriguez | C21: Chair | D21: Furniture | E21: East | F21: 7 | G21: 581.16 | H21: 4068.12 | I21: 2668.67 | J21: 1399.45 | K21: 45805 | L21: 45814 | M21: Akhil | N21: 4 | O21: 11:20:00 | P21: 8.1 | Q21: =RIGHT(A21,"4") -> 0020 | R21: =IF('RETAIL SALES DATA.'!H21>AVERAGE('RETAIL SALES DATA.'!H21:H1020),"HIGHEST VALUE","LOWEST VALUE") -> LOWEST VALUE | S21: =IF(J21>0,"Profit","Loss") -> Profit | T21: =PROPER(B21) -> Sean Rodriguez | U21: =PROPER(C21) -> Chair | V21: =YEAR(K21) -> 2025 | W21: =MONTH(L21) -> 6 | X21: =DAY(K21) -> 28 | Y21: =TEXT(K21,"MMM") -> May | Z21: =L21-K21 -> 9 | AB21: Oct | AC21: =SUMIFS($H$2:$H$1001,$Y$2:$Y$1001,AB21,$V$2:$V$1001,V995) -> 0 | AD21: =SUMIFS($H$2:$H$1001,$Y$2:$Y$1001,AB21,$V$2:$V$1001,V999) -> 1137093.4 | AE21: =SUMIFS($H$2:$H$1001,$Y$2:$Y$1001,AB21,$V$2:$V$1001,V12) -> 1301211.4
A22: ORD0021 | B22: Joseph Mora | C22: Laptop | D22: Electronics | E22: East | F22: 16 | G22: 3094.38 | H22: 49510.08 | I22: 33974.06 | J22: 15536.02 | K22: 45623 | L22: 45626 | M22: Megha | N22: 1 | O22: 10:52:00 | P22: 6.7 | Q22: =RIGHT(A22,"4") -> 0021 | R22: =IF('RETAIL SALES DATA.'!H22>AVERAGE('RETAIL SALES DATA.'!H22:H1021),"HIGHEST VALUE","LOWEST VALUE") -> HIGHEST VALUE | S22: =IF(J22>0,"Profit","Loss") -> Profit | T22: =PROPER(B22) -> Joseph Mora | U22: =PROPER(C22) -> Laptop | V22: =YEAR(K22) -> 2024 | W22: =MONTH(L22) -> 11 | X22: =DAY(K22) -> 27 | Y22: =TEXT(K22,"MMM") -> Nov | Z22: =L22-K22 -> 3 | AB22: Nov | AC22: =SUMIFS($H$2:$H$1001,$Y$2:$Y$1001,AB22,$V$2:$V$1001,V996) -> 1086755.5 | AD22: =SUMIFS($H$2:$H$1001,$Y$2:$Y$1001,AB22,$V$2:$V$1001,V1000) -> 0 | AE22: =SUMIFS($H$2:$H$1001,$Y$2:$Y$1001,AB22,$V$2:$V$1001,V13) -> 1086755.5
A23: ORD0022 | B23: Deborah Hernandez | C23: Cupboard | D23: Furniture | E23: East | F23: 17 | G23: 4018.59 | H23: 68316.03 | I23: 51272.8 | J23: 17043.23 | K23: 46092 | L23: 46101 | M23: Diya | N23: 5 | O23: 09:23:00 | P23: 7.1 | Q23: =RIGHT(A23,"4") -> 0022 | R23: =IF('RETAIL SALES DATA.'!H23>AVERAGE('RETAIL SALES DATA.'!H23:H1022),"HIGHEST VALUE","LOWEST VALUE") -> HIGHEST VALUE | S23: =IF(J23>0,"Profit","Loss") -> Profit | T23: =PROPER(B23) -> Deborah Hernandez | U23: =PROPER(C23) -> Cupboard | V23: =YEAR(K23) -> 2026 | W23: =MONTH(L23) -> 3 | X23: =DAY(K23) -> 11 | Y23: =TEXT(K23,"MMM") -> Mar | Z23: =L23-K23 -> 9 | AB23: Dec | AC23: =SUMIFS($H$2:$H$1001,$Y$2:$Y$1001,AB23,$V$2:$V$1001,V997) -> 1027155.3 | AD23: =SUMIFS($H$2:$H$1001,$Y$2:$Y$1001,AB23,$V$2:$V$1001,V1001) -> 1027155.3 | AE23: =SUMIFS($H$2:$H$1001,$Y$2:$Y$1001,AB23,$V$2:$V$1001,V14) -> 1027155.3
A24: ORD0023 | B24: Elizabeth Moore | C24: Printer | D24: Office Supplies | E24: North | F24: 6 | G24: 3184.36 | H24: 19106.16 | I24: 10404.21 | J24: 8701.95 | K24: 45826 | L24: 45832 | M24: Sneha | N24: 5 | O24: 11:43:00 | P24: 6.3 | Q24: =RIGHT(A24,"4") -> 0023 | R24: =IF('RETAIL SALES DATA.'!H24>AVERAGE('RETAIL SALES DATA.'!H24:H1023),"HIGHEST VALUE","LOWEST VALUE") -> LOWEST VALUE | S24: =IF(J24>0,"Profit","Loss") -> Profit | T24: =PROPER(B24) -> Elizabeth Moore | U24: =PROPER(C24) -> Printer | V24: =YEAR(K24) -> 2025 | W24: =MONTH(L24) -> 6 | X24: =DAY(K24) -> 18 | Y24: =TEXT(K24,"MMM") -> Jun | Z24: =L24-K24 -> 6
A25: ORD0024 | B25: Melissa Davis | C25: Desk | D25: Furniture | E25: North | F25: 20 | G25: 267.78 | H25: 5355.6 | I25: 2790.07 | J25: 2565.53 | K25: 45603 | L25: 45613 | M25: Megha | N25: 5 | O25: 11:42:00 | P25: 7.6 | Q25: =RIGHT(A25,"4") -> 0024 | R25: =IF('RETAIL SALES DATA.'!H25>AVERAGE('RETAIL SALES DATA.'!H25:H1024),"HIGHEST VALUE","LOWEST VALUE") -> LOWEST VALUE | S25: =IF(J25>0,"Profit","Loss") -> Profit | T25: =PROPER(B25) -> Melissa Davis | U25: =PROPER(C25) -> Desk | V25: =YEAR(K25) -> 2024 | W25: =MONTH(L25) -> 11 | X25: =DAY(K25) -> 7 | Y25: =TEXT(K25,"MMM") -> Nov | Z25: =L25-K25 -> 10
A26: ORD0025 | B26: Andrew Gould | C26: Chair | D26: Furniture | E26: South | F26: 18 | G26: 1973.33 | H26: 35519.94 | I26: 18379.63 | J26: 17140.31 | K26: 45520 | L26: 45521 | M26: Fathima | N26: 3 | O26: 10:39:00 | P26: 8.3 | Q26: =RIGHT(A26,"4") -> 0025 | R26: =IF('RETAIL SALES DATA.'!H26>AVERAGE('RETAIL SALES DATA.'!H26:H1025),"HIGHEST VALUE","LOWEST VALUE") -> HIGHEST VALUE | S26: =IF(J26>0,"Profit","Loss") -> Profit | T26: =PROPER(B26) -> Andrew Gould | U26: =PROPER(C26) -> Chair | V26: =YEAR(K26) -> 2024 | W26: =MONTH(L26) -> 8 | X26: =DAY(K26) -> 16 | Y26: =TEXT(K26,"MMM") -> Aug | Z26: =L26-K26 -> 1
A27: ORD0026 | B27: Glen Scott | C27: Pen | D27: Office Supplies | E27: North | F27: 10 | G27: 4872.29 | H27: 48722.9 | I27: 30720.08 | J27: 18002.82 | K27: 45807 | L27: 45814 | M27: Akhil | N27: 3 | O27: 10:07:00 | P27: 6.8 | Q27: =RIGHT(A27,"4") -> 0026 | R27: =IF('RETAIL SALES DATA.'!H27>AVERAGE('RETAIL SALES DATA.'!H27:H1026),"HIGHEST VALUE","LOWEST VALUE") -> HIGHEST VALUE | S27: =IF(J27>0,"Profit","Loss") -> Profit | T27: =PROPER(B27) -> Glen Scott | U27: =PROPER(C27) -> Pen | V27: =YEAR(K27) -> 2025 | W27: =MONTH(L27) -> 6 | X27: =DAY(K27) -> 30 | Y27: =TEXT(K27,"MMM") -> May | Z27: =L27-K27 -> 7
A28: ORD0027 | B28: Isaac Fisher | C28: Notebook | D28: Office Supplies | E28: West | F28: 12 | G28: 3399.13 | H28: 40789.56 | I28: 26160.75 | J28: 14628.81 | K28: 45643 | L28: 45645 | M28: Diya | N28: 3 | O28: 10:46:00 | P28: 6.9 | Q28: =RIGHT(A28,"4") -> 0027 | R28: =IF('RETAIL SALES DATA.'!H28>AVERAGE('RETAIL SALES DATA.'!H28:H1027),"HIGHEST VALUE","LOWEST VALUE") -> HIGHEST VALUE | S28: =IF(J28>0,"Profit","Loss") -> Profit | T28: =PROPER(B28) -> Isaac Fisher | U28: =PROPER(C28) -> Notebook | V28: =YEAR(K28) -> 2024 | W28: =MONTH(L28) -> 12 | X28: =DAY(K28) -> 17 | Y28: =TEXT(K28,"MMM") -> Dec | Z28: =L28-K28 -> 2
A29: ORD0028 | B29: Matthew Hanson | C29: Laptop | D29: Electronics | E29: East | F29: 19 | G29: 352.92 | H29: 6705.48 | I29: 3564.37 | J29: 3141.11 | K29: 45666 | L29: 45675 | M29: Nikhil | N29: 2 | O29: 08:32:00 | P29: 8.5 | Q29: =RIGHT(A29,"4") -> 0028 | R29: =IF('RETAIL SALES DATA.'!H29>AVERAGE('RETAIL SALES DATA.'!H29:H1028),"HIGHEST VALUE","LOWEST VALUE") -> LOWEST VALUE | S29: =IF(J29>0,"Profit","Loss") -> Profit | T29: =PROPER(B29) -> Matthew Hanson | U29: =PROPER(C29) -> Laptop | V29: =YEAR(K29) -> 2025 | W29: =MONTH(L29) -> 1 | X29: =DAY(K29) -> 9 | Y29: =TEXT(K29,"MMM") -> Jan | Z29: =L29-K29 -> 9
A30: ORD0029 | B30: Jamie Benton | C30: Notebook | D30: Office Supplies | E30: West | F30: 18 | G30: 1397.43 | H30: 25153.74 | I30: 16703.28 | J30: 8450.46 | K30: 45843 | L30: 45846 | M30: Megha | N30: 2 | O30: 10:55:00 | P30: 8.9 | Q30: =RIGHT(A30,"4") -> 0029 | R30: =IF('RETAIL SALES DATA.'!H30>AVERAGE('RETAIL SALES DATA.'!H30:H1029),"HIGHEST VALUE","LOWEST VALUE") -> LOWEST VALUE | S30: =IF(J30>0,"Profit","Loss") -> Profit | T30: =PROPER(B30) -> Jamie Benton | U30: =PROPER(C30) -> Notebook | V30: =YEAR(K30) -> 2025 | W30: =MONTH(L30) -> 7 | X30: =DAY(K30) -> 5 | Y30: =TEXT(K30,"MMM") -> Jul | Z30: =L30-K30 -> 3
A31: ORD0030 | B31: Kristy Sullivan | C31: Pen | D31: Office Supplies | E31: South | F31: 17 | G31: 4186.24 | H31: 71166.08 | I31: 58945.05 | J31: 12221.03 | K31: 45813 | L31: 45819 | M31: Fathima | N31: 4 | O31: 10:42:00 | P31: 6.3 | Q31: =RIGHT(A31,"4") -> 0030 | R31: =IF('RETAIL SALES DATA.'!H31>AVERAGE('RETAIL SALES DATA.'!H31:H1030),"HIGHEST VALUE","LOWEST VALUE") -> HIGHEST VALUE | S31: =IF(J31>0,"Profit","Loss") -> Profit | T31: =PROPER(B31) -> Kristy Sullivan | U31: =PROPER(C31) -> Pen | V31: =YEAR(K31) -> 2025 | W31: =MONTH(L31) -> 6 | X31: =DAY(K31) -> 5 | Y31: =TEXT(K31,"MMM") -> Jun | Z31: =L31-K31 -> 6 | AC31: MAXIMUM DELIVERY DAYS | AD31: =MAX(Table13[DELIVERY DATE]) -> 10
A32: ORD0031 | B32: Carolyn Scott | C32: Pen | D32: Office Supplies | E32: West | F32: 1 | G32: 2612.03 | H32: 2612.03 | I32: 1575.12 | J32: 1036.91 | K32: 45480 | L32: 45485 | M32: Vivek | N32: 3 | O32: 10:01:00 | P32: 6.5 | Q32: =RIGHT(A32,"4") -> 0031 | R32: =IF('RETAIL SALES DATA.'!H32>AVERAGE('RETAIL SALES DATA.'!H32:H1031),"HIGHEST VALUE","LOWEST VALUE") -> LOWEST VALUE | S32: =IF(J32>0,"Profit","Loss") -> Profit | T32: =PROPER(B32) -> Carolyn Scott | U32: =PROPER(C32) -> Pen | V32: =YEAR(K32) -> 2024 | W32: =MONTH(L32) -> 7 | X32: =DAY(K32) -> 7 | Y32: =TEXT(K32,"MMM") -> Jul | Z32: =L32-K32 -> 5 | AC32: MINIMUM DELIVERY DAYS | AD32: =MIN(Table13[DELIVERY DATE]) -> 1
A33: ORD0032 | B33: Mary Day | C33: Chair | D33: Furniture | E33: West | F33: 13 | G33: 3740.17 | H33: 48622.21 | I33: 41341.16 | J33: 7281.05 | K33: 45808 | L33: 45812 | M33: Rahul | N33: 3 | O33: 08:27:00 | P33: 6.3 | Q33: =RIGHT(A33,"4") -> 0032 | R33: =IF('RETAIL SALES DATA.'!H33>AVERAGE('RETAIL SALES DATA.'!H33:H1032),"HIGHEST VALUE","LOWEST VALUE") -> HIGHEST VALUE | S33: =IF(J33>0,"Profit","Loss") -> Profit | T33: =PROPER(B33) -> Mary Day | U33: =PROPER(C33) -> Chair | V33: =YEAR(K33) -> 2025 | W33: =MONTH(L33) -> 6 | X33: =DAY(K33) -> 31 | Y33: =TEXT(K33,"MMM") -> May | Z33: =L33-K33 -> 4 | AI33: MONTHS
A34: ORD0033 | B34: Matthew Fernandez | C34: Sofa | D34: Furniture | E34: East | F34: 12 | G34: 3480.93 | H34: 41771.16 | I34: 23955 | J34: 17816.16 | K34: 46026 | L34: 46032 | M34: Rahul | N34: 2 | O34: 11:34:00 | P34: 7 | Q34: =RIGHT(A34,"4") -> 0033 | R34: =IF('RETAIL SALES DATA.'!H34>AVERAGE('RETAIL SALES DATA.'!H34:H1033),"HIGHEST VALUE","LOWEST VALUE") -> HIGHEST VALUE | S34: =IF(J34>0,"Profit","Loss") -> Profit | T34: =PROPER(B34) -> Matthew Fernandez | U34: =PROPER(C34) -> Sofa | V34: =YEAR(K34) -> 2026 | W34: =MONTH(L34) -> 1 | X34: =DAY(K34) -> 4 | Y34: =TEXT(K34,"MMM") -> Jan | Z34: =L34-K34 -> 6 | AI34: Jan
A35: ORD0034 | B35: Tonya Gallegos | C35: Printer | D35: Office Supplies | E35: West | F35: 18 | G35: 4419.1 | H35: 79543.8 | I35: 47654.84 | J35: 31888.96 | K35: 45629 | L35: 45639 | M35: Fathima | N35: 4 | O35: 10:16:00 | P35: 7.7 | Q35: =RIGHT(A35,"4") -> 0034 | R35: =IF('RETAIL SALES DATA.'!H35>AVERAGE('RETAIL SALES DATA.'!H35:H1034),"HIGHEST VALUE","LOWEST VALUE") -> HIGHEST VALUE | S35: =IF(J35>0,"Profit","Loss") -> Profit | T35: =PROPER(B35) -> Tonya Gallegos | U35: =PROPER(C35) -> Printer | V35: =YEAR(K35) -> 2024 | W35: =MONTH(L35) -> 12 | X35: =DAY(K35) -> 3 | Y35: =TEXT(K35,"MMM") -> Dec | Z35: =L35-K35 -> 10 | AI35: Feb
A36: ORD0035 | B36: Jody Black | C36: File | D36: Office Supplies | E36: South | F36: 10 | G36: 4243.55 | H36: 42435.5 | I36: 29127.76 | J36: 13307.74 | K36: 45916 | L36: 45925 | M36: Akhil | N36: 2 | O36: 11:25:00 | P36: 9.4 | Q36: =RIGHT(A36,"4") -> 0035 | R36: =IF('RETAIL SALES DATA.'!H36>AVERAGE('RETAIL SALES DATA.'!H36:H1035),"HIGHEST VALUE","LOWEST VALUE") -> HIGHEST VALUE | S36: =IF(J36>0,"Profit","Loss") -> Profit | T36: =PROPER(B36) -> Jody Black | U36: =PROPER(C36) -> File | V36: =YEAR(K36) -> 2025 | W36: =MONTH(L36) -> 9 | X36: =DAY(K36) -> 16 | Y36: =TEXT(K36,"MMM") -> Sep | Z36: =L36-K36 -> 9 | AI36: Mar
A37: ORD0036 | B37: Laurie Flores | C37: File | D37: Office Supplies | E37: East | F37: 16 | G37: 2535.18 | H37: 40562.88 | I37: 31992.98 | J37: 8569.9 | K37: 46117 | L37: 46121 | M37: Diya | N37: 2 | O37: 11:39:00 | P37: 9.4 | Q37: =RIGHT(A37,"4") -> 0036 | R37: =IF('RETAIL SALES DATA.'!H37>AVERAGE('RETAIL SALES DATA.'!H37:H1036),"HIGHEST VALUE","LOWEST VALUE") -> HIGHEST VALUE | S37: =IF(J37>0,"Profit","Loss") -> Profit | T37: =PROPER(B37) -> Laurie Flores | U37: =PROPER(C37) -> File | V37: =YEAR(K37) -> 2026 | W37: =MONTH(L37) -> 4 | X37: =DAY(K37) -> 5 | Y37: =TEXT(K37,"MMM") -> Apr | Z37: =L37-K37 -> 4 | AC37: =SUMIF(Table13[YEAR],V987,H2:H1001) -> 13413606 | AI37: Apr
A38: ORD0037 | B38: Charles Logan | C38: Mouse | D38: Electronics | E38: West | F38: 10 | G38: 2467.57 | H38: 24675.7 | I38: 16242.09 | J38: 8433.61 | K38: 45913 | L38: 45917 | M38: Rahul | N38: 3 | O38: 08:56:00 | P38: 6.1 | Q38: =RIGHT(A38,"4") -> 0037 | R38: =IF('RETAIL SALES DATA.'!H38>AVERAGE('RETAIL SALES DATA.'!H38:H1037),"HIGHEST VALUE","LOWEST VALUE") -> LOWEST VALUE | S38: =IF(J38>0,"Profit","Loss") -> Profit | T38: =PROPER(B38) -> Charles Logan | U38: =PROPER(C38) -> Mouse | V38: =YEAR(K38) -> 2025 | W38: =MONTH(L38) -> 9 | X38: =DAY(K38) -> 13 | Y38: =TEXT(K38,"MMM") -> Sep | Z38: =L38-K38 -> 4 | AI38: May
A39: ORD0038 | B39: Lori Petersen | C39: Sofa | D39: Furniture | E39: South | F39: 7 | G39: 3511.87 | H39: 24583.09 | I39: 14650.99 | J39: 9932.1 | K39: 45726 | L39: 45728 | M39: Rahul | N39: 5 | O39: 09:54:00 | P39: 7.5 | Q39: =RIGHT(A39,"4") -> 0038 | R39: =IF('RETAIL SALES DATA.'!H39>AVERAGE('RETAIL SALES DATA.'!H39:H1038),"HIGHEST VALUE","LOWEST VALUE") -> LOWEST VALUE | S39: =IF(J39>0,"Profit","Loss") -> Profit | T39: =PROPER(B39) -> Lori Petersen | U39: =PROPER(C39) -> Sofa | V39: =YEAR(K39) -> 2025 | W39: =MONTH(L39) -> 3 | X39: =DAY(K39) -> 10 | Y39: =TEXT(K39,"MMM") -> Mar | Z39: =L39-K39 -> 2 | AI39: Jun
A40: ORD0039 | B40: Roger Gutierrez | C40: Chair | D40: Furniture | E40: North | F40: 3 | G40: 2167.58 | H40: 6502.74 | I40: 5214.81 | J40: 1287.93 | K40: 45752 | L40: 45761 | M40: Fathima | N40: 5 | O40: 09:13:00 | P40: 8.4 | Q40: =RIGHT(A40,"4") -> 0039 | R40: =IF('RETAIL SALES DATA.'!H40>AVERAGE('RETAIL SALES DATA.'!H40:H1039),"HIGHEST VALUE","LOWEST VALUE") -> LOWEST VALUE | S40: =IF(J40>0,"Profit","Loss") -> Profit | T40: =PROPER(B40) -> Roger Gutierrez | U40: =PROPER(C40) -> Chair | V40: =YEAR(K40) -> 2025 | W40: =MONTH(L40) -> 4 | X40: =DAY(K40) -> 5 | Y40: =TEXT(K40,"MMM") -> Apr | Z40: =L40-K40 -> 9 | AI40: Jul
A41: ORD0040 | B41: Arthur Anderson | C41: Pen | D41: Office Supplies | E41: West | F41: 2 | G41: 326.99 | H41: 653.98 | I41: 374.73 | J41: 279.25 | K41: 45799 | L41: 45803 | M41: Arun | N41: 1 | O41: 11:15:00 | P41: 6.8 | Q41: =RIGHT(A41,"4") -> 0040 | R41: =IF('RETAIL SALES DATA.'!H41>AVERAGE('RETAIL SALES DATA.'!H41:H1040),"HIGHEST VALUE","LOWEST VALUE") -> LOWEST VALUE | S41: =IF(J41>0,"Profit","Loss") -> Profit | T41: =PROPER(B41) -> Arthur Anderson | U41: =PROPER(C41) -> Pen | V41: =YEAR(K41) -> 2025 | W41: =MONTH(L41) -> 5 | X41: =DAY(K41) -> 22 | Y41: =TEXT(K41,"MMM") -> May | Z41: =L41-K41 -> 4 | AI41: Aug
A42: ORD0041 | B42: April Schmidt | C42: Marker | D42: Office Supplies | E42: North | F42: 12 | G42: 1376.34 | H42: 16516.08 | I42: 10337.79 | J42: 6178.29 | K42: 45635 | L42: 45637 | M42: Diya | N42: 5 | O42: 08:13:00 | P42: 8.2 | Q42: =RIGHT(A42,"4") -> 0041 | R42: =IF('RETAIL SALES DATA.'!H42>AVERAGE('RETAIL SALES DATA.'!H42:H1041),"HIGHEST VALUE","LOWEST VALUE") -> LOWEST VALUE | S42: =IF(J42>0,"Profit","Loss") -> Profit | T42: =PROPER(B42) -> April Schmidt | U42: =PROPER(C42) -> Marker | V42: =YEAR(K42) -> 2024 | W42: =MONTH(L42) -> 12 | X42: =DAY(K42) -> 9 | Y42: =TEXT(K42,"MMM") -> Dec | Z42: =L42-K42 -> 2 | AI42: Sep
A43: ORD0042 | B43: Amanda Holmes | C43: Table | D43: Furniture | E43: South | F43: 8 | G43: 2932.22 | H43: 23457.76 | I43: 13646.01 | J43: 9811.75 | K43: 45992 | L43: 45994 | M43: Rahul | N43: 3 | O43: 11:50:00 | P43: 6.1 | Q43: =RIGHT(A43,"4") -> 0042 | R43: =IF('RETAIL SALES DATA.'!H43>AVERAGE('RETAIL SALES DATA.'!H43:H1042),"HIGHEST VALUE","LOWEST VALUE") -> LOWEST VALUE | S43: =IF(J43>0,"Profit","Loss") -> Profit | T43: =PROPER(B43) -> Amanda Holmes | U43: =PROPER(C43) -> Table | V43: =YEAR(K43) -> 2025 | W43: =MONTH(L43) -> 12 | X43: =DAY(K43) -> 1 | Y43: =TEXT(K43,"MMM") -> Dec | Z43: =L43-K43 -> 2 | AE43: {=_xlfn.UNIQUE(Table13[MONTH2])} -> Sep | AI43: Oct
A44: ORD0043 | B44: Emily Norton | C44: Keyboard | D44: Electronics | E44: North | F44: 5 | G44: 3777.49 | H44: 18887.45 | I44: 10978.7 | J44: 7908.75 | K44: 46132 | L44: 46135 | M44: Nikhil | N44: 2 | O44: 10:26:00 | P44: 6.1 | Q44: =RIGHT(A44,"4") -> 0043 | R44: =IF('RETAIL SALES DATA.'!H44>AVERAGE('RETAIL SALES DATA.'!H44:H1043),"HIGHEST VALUE","LOWEST VALUE") -> LOWEST VALUE | S44: =IF(J44>0,"Profit","Loss") -> Profit | T44: =PROPER(B44) -> Emily Norton | U44: =PROPER(C44) -> Keyboard | V44: =YEAR(K44) -> 2026 | W44: =MONTH(L44) -> 4 | X44: =DAY(K44) -> 20 | Y44: =TEXT(K44,"MMM") -> Apr | Z44: =L44-K44 -> 3 | AE44: Jan | AI44: Nov
A45: ORD0044 | B45: Rachel Hooper | C45: Keyboard | D45: Electronics | E45: South | F45: 3 | G45: 1195.02 | H45: 3585.06 | I45: 2786.04 | J45: 799.02 | K45: 46007 | L45: 46016 | M45: Nikhil | N45: 4 | O45: 09:40:00 | P45: 7.7 | Q45: =RIGHT(A45,"4") -> 0044 | R45: =IF('RETAIL SALES DATA.'!H45>AVERAGE('RETAIL SALES DATA.'!H45:H1044),"HIGHEST VALUE","LOWEST VALUE") -> LOWEST VALUE | S45: =IF(J45>0,"Profit","Loss") -> Profit | T45: =PROPER(B45) -> Rachel Hooper | U45: =PROPER(C45) -> Keyboard | V45: =YEAR(K45) -> 2025 | W45: =MONTH(L45) -> 12 | X45: =DAY(K45) -> 16 | Y45: =TEXT(K45,"MMM") -> Dec | Z45: =L45-K45 -> 9 | AE45: May | AI45: Dec
A46: ORD0045 | B46: Douglas Herman | C46: Printer | D46: Office Supplies | E46: South | F46: 14 | G46: 1904.14 | H46: 26657.96 | I46: 19571.08 | J46: 7086.88 | K46: 45538 | L46: 45544 | M46: Fathima | N46: 2 | O46: 08:38:00 | P46: 8.9 | Q46: =RIGHT(A46,"4") -> 0045 | R46: =IF('RETAIL SALES DATA.'!H46>AVERAGE('RETAIL SALES DATA.'!H46:H1045),"HIGHEST VALUE","LOWEST VALUE") -> HIGHEST VALUE | S46: =IF(J46>0,"Profit","Loss") -> Profit | T46: =PROPER(B46) -> Douglas Herman | U46: =PROPER(C46) -> Printer | V46: =YEAR(K46) -> 2024 | W46: =MONTH(L46) -> 9 | X46: =DAY(K46) -> 3 | Y46: =TEXT(K46,"MMM") -> Sep | Z46: =L46-K46 -> 6 | AE46: Jul
A47: ORD0046 | B47: Rebecca Hawkins | C47: Mouse | D47: Electronics | E47: South | F47: 7 | G47: 1040.8 | H47: 7285.6 | I47: 5260.34 | J47: 2025.26 | K47: 45606 | L47: 45616 | M47: Fathima | N47: 2 | O47: 08:54:00 | P47: 7.3 | Q47: =RIGHT(A47,"4") -> 0046 | R47: =IF('RETAIL SALES DATA.'!H47>AVERAGE('RETAIL SALES DATA.'!H47:H1046),"HIGHEST VALUE","LOWEST VALUE") -> LOWEST VALUE | S47: =IF(J47>0,"Profit","Loss") -> Profit | T47: =PROPER(B47) -> Rebecca Hawkins | U47: =PROPER(C47) -> Mouse | V47: =YEAR(K47) -> 2024 | W47: =MONTH(L47) -> 11 | X47: =DAY(K47) -> 10 | Y47: =TEXT(K47,"MMM") -> Nov | Z47: =L47-K47 -> 10 | AE47: Nov
A48: ORD0047 | B48: Shannon Harris | C48: Mouse | D48: Electronics | E48: East | F48: 3 | G48: 1841.45 | H48: 5524.35 | I48: 4436.67 | J48: 1087.68 | K48: 46082 | L48: 46086 | M48: Anjali | N48: 3 | O48: 08:56:00 | P48: 8.3 | Q48: =RIGHT(A48,"4") -> 0047 | R48: =IF('RETAIL SALES DATA.'!H48>AVERAGE('RETAIL SALES DATA.'!H48:H1047),"HIGHEST VALUE","LOWEST VALUE") -> LOWEST VALUE | S48: =IF(J48>0,"Profit","Loss") -> Profit | T48: =PROPER(B48) -> Shannon Harris | U48: =PROPER(C48) -> Mouse | V48: =YEAR(K48) -> 2026 | W48: =MONTH(L48) -> 3 | X48: =DAY(K48) -> 1 | Y48: =TEXT(K48,"MMM") -> Mar | Z48: =L48-K48 -> 4 | AE48: Feb
A49: ORD0048 | B49: Jennifer Maxwell | C49: Notebook | D49: Office Supplies | E49: North | F49: 6 | G49: 3881.06 | H49: 23286.36 | I49: 19228.59 | J49: 4057.77 | K49: 45779 | L49: 45789 | M49: Nikhil | N49: 1 | O49: 11:26:00 | P49: 8.2 | Q49: =RIGHT(A49,"4") -> 0048 | R49: =IF('RETAIL SALES DATA.'!H49>AVERAGE('RETAIL SALES DATA.'!H49:H1048),"HIGHEST VALUE","LOWEST VALUE") -> LOWEST VALUE | S49: =IF(J49>0,"Profit","Loss") -> Profit | T49: =PROPER(B49) -> Jennifer Maxwell | U49: =PROPER(C49) -> Notebook | V49: =YEAR(K49) -> 2025 | W49: =MONTH(L49) -> 5 | X49: =DAY(K49) -> 2 | Y49: =TEXT(K49,"MMM") -> May | Z49: =L49-K49 -> 10 | AE49: Dec
A50: ORD0049 | B50: Melissa Edwards | C50: Desk | D50: Furniture | E50: South | F50: 17 | G50: 4410.57 | H50: 74979.69 | I50: 59559.51 | J50: 15420.18 | K50: 45701 | L50: 45703 | M50: Anjali | N50: 5 | O50: 10:17:00 | P50: 9.6 | Q50: =RIGHT(A50,"4") -> 0049 | R50: =IF('RETAIL SALES DATA.'!H50>AVERAGE('RETAIL SALES DATA.'!H50:H1049),"HIGHEST VALUE","LOWEST VALUE") -> HIGHEST VALUE | S50: =IF(J50>0,"Profit","Loss") -> Profit | T50: =PROPER(B50) -> Melissa Edwards | U50: =PROPER(C50) -> Desk | V50: =YEAR(K50) -> 2025 | W50: =MONTH(L50) -> 2 | X50: =DAY(K50) -> 13 | Y50: =TEXT(K50,"MMM") -> Feb | Z50: =L50-K50 -> 2 | AE50: Jun
A51: ORD0050 | B51: Heather Campbell | C51: Printer | D51: Office Supplies | E51: South | F51: 1 | G51: 4982.5 | H51: 4982.5 | I51: 4359.99 | J51: 622.51 | K51: 45787 | L51: 45790 | M51: Vivek | N51: 2 | O51: 09:13:00 | P51: 9.5 | Q51: =RIGHT(A51,"4") -> 0050 | R51: =IF('RETAIL SALES DATA.'!H51>AVERAGE('RETAIL SALES DATA.'!H51:H1050),"HIGHEST VALUE","LOWEST VALUE") -> LOWEST VALUE | S51: =IF(J51>0,"Profit","Loss") -> Profit | T51: =PROPER(B51) -> Heather Campbell | U51: =PROPER(C51) -> Printer | V51: =YEAR(K51) -> 2025 | W51: =MONTH(L51) -> 5 | X51: =DAY(K51) -> 10 | Y51: =TEXT(K51,"MMM") -> May | Z51: =L51-K51 -> 3 | AE51: Mar
A52: ORD0051 | B52: James Green | C52: File | D52: Office Supplies | E52: South | F52: 14 | G52: 2778.81 | H52: 38903.34 | I52: 31496.68 | J52: 7406.66 | K52: 45757 | L52: 45767 | M52: Sneha | N52: 4 | O52: 08:43:00 | P52: 9.7 | Q52: =RIGHT(A52,"4") -> 0051 | R52: =IF('RETAIL SALES DATA.'!H52>AVERAGE('RETAIL SALES DATA.'!H52:H1051),"HIGHEST VALUE","LOWEST VALUE") -> HIGHEST VALUE | S52: =IF(J52>0,"Profit","Loss") -> Profit | T52: =PROPER(B52) -> James Green | U52: =PROPER(C52) -> File | V52: =YEAR(K52) -> 2025 | W52: =MONTH(L52) -> 4 | X52: =DAY(K52) -> 10 | Y52: =TEXT(K52,"MMM") -> Apr | Z52: =L52-K52 -> 10 | AE52: Apr
A53: ORD0052 | B53: Ashley Bowman | C53: Monitor | D53: Electronics | E53: South | F53: 19 | G53: 401.55 | H53: 7629.45 | I53: 5247.09 | J53: 2382.36 | K53: 46156 | L53: 46160 | M53: Akhil | N53: 4 | O53: 09:37:00 | P53: 7.1 | Q53: =RIGHT(A53,"4") -> 0052 | R53: =IF('RETAIL SALES DATA.'!H53>AVERAGE('RETAIL SALES DATA.'!H53:H1052),"HIGHEST VALUE","LOWEST VALUE") -> LOWEST VALUE | S53: =IF(J53>0,"Profit","Loss") -> Profit | T53: =PROPER(B53) -> Ashley Bowman | U53: =PROPER(C53) -> Monitor | V53: =YEAR(K53) -> 2026 | W53: =MONTH(L53) -> 5 | X53: =DAY(K53) -> 14 | Y53: =TEXT(K53,"MMM") -> May | Z53: =L53-K53 -> 4 | AE53: Aug
A54: ORD0053 | B54: William Allen | C54: Mouse | D54: Electronics | E54: West | F54: 9 | G54: 1650.29 | H54: 14852.61 | I54: 10439.91 | J54: 4412.7 | K54: 46143 | L54: 46144 | M54: Megha | N54: 2 | O54: 11:45:00 | P54: 6 | Q54: =RIGHT(A54,"4") -> 0053 | R54: =IF('RETAIL SALES DATA.'!H54>AVERAGE('RETAIL SALES DATA.'!H54:H1053),"HIGHEST VALUE","LOWEST VALUE") -> LOWEST VALUE | S54: =IF(J54>0,"Profit","Loss") -> Profit | T54: =PROPER(B54) -> William Allen | U54: =PROPER(C54) -> Mouse | V54: =YEAR(K54) -> 2026 | W54: =MONTH(L54) -> 5 | X54: =DAY(K54) -> 1 | Y54: =TEXT(K54,"MMM") -> May | Z54: =L54-K54 -> 1 | AE54: Oct
A55: ORD0054 | B55: Christina Henderson | C55: Laptop | D55: Electronics | E55: East | F55: 1 | G55: 3547.8 | H55: 3547.8 | I55: 2503.42 | J55: 1044.38 | K55: 45745 | L55: 45749 | M55: Nikhil | N55: 4 | O55: 08:57:00 | P55: 8 | Q55: =RIGHT(A55,"4") -> 0054 | R55: =IF('RETAIL SALES DATA.'!H55>AVERAGE('RETAIL SALES DATA.'!H55:H1054),"HIGHEST VALUE","LOWEST VALUE") -> LOWEST VALUE | S55: =IF(J55>0,"Profit","Loss") -> Profit | T55: =PROPER(B55) -> Christina Henderson | U55: =PROPER(C55) -> Laptop | V55: =YEAR(K55) -> 2025 | W55: =MONTH(L55) -> 4 | X55: =DAY(K55) -> 29 | Y55: =TEXT(K55,"MMM") -> Mar | Z55: =L55-K55 -> 4
A56: ORD0055 | B56: Brian Simon | C56: Marker | D56: Office Supplies | E56: East | F56: 15 | G56: 797.77 | H56: 11966.55 | I56: 7761.32 | J56: 4205.23 | K56: 46008 | L56: 46015 | M56: Megha | N56: 5 | O56: 11:38:00 | P56: 6.7 | Q56: =RIGHT(A56,"4") -> 0055 | R56: =IF('RETAIL SALES DATA.'!H56>AVERAGE('RETAIL SALES DATA.'!H56:H1055),"HIGHEST VALUE","LOWEST VALUE") -> LOWEST VALUE | S56: =IF(J56>0,"Profit","Loss") -> Profit | T56: =PROPER(B56) -> Brian Simon | U56: =PROPER(C56) -> Marker | V56: =YEAR(K56) -> 2025 | W56: =MONTH(L56) -> 12 | X56: =DAY(K56) -> 17 | Y56: =TEXT(K56,"MMM") -> Dec | Z56: =L56-K56 -> 7
A57: ORD0056 | B57: Marc Martinez | C57: Marker | D57: Office Supplies | E57: North | F57: 14 | G57: 3390.11 | H57: 47461.54 | I57: 33888.91 | J57: 13572.63 | K57: 46096 | L57: 46105 | M57: Anjali | N57: 3 | O57: 11:48:00 | P57: 9.4 | Q57: =RIGHT(A57,"4") -> 0056 | R57: =IF('RETAIL SALES DATA.'!H57>AVERAGE('RETAIL SALES DATA.'!H57:H1056),"HIGHEST VALUE","LOWEST VALUE") -> HIGHEST VALUE | S57: =IF(J57>0,"Profit","Loss") -> Profit | T57: =PROPER(B57) -> Marc Martinez | U57: =PROPER(C57) -> Marker | V57: =YEAR(K57) -> 2026 | W57: =MONTH(L57) -> 3 | X57: =DAY(K57) -> 15 | Y57: =TEXT(K57,"MMM") -> Mar | Z57: =L57-K57 -> 9
A58: ORD0057 | B58: Rose Garcia | C58: Table | D58: Furniture | E58: South | F58: 16 | G58: 4225.43 | H58: 67606.88 | I58: 36274.63 | J58: 31332.25 | K58: 45734 | L58: 45742 | M58: Megha | N58: 2 | O58: 10:48:00 | P58: 6.2 | Q58: =RIGHT(A58,"4") -> 0057 | R58: =IF('RETAIL SALES DATA.'!H58>AVERAGE('RETAIL SALES DATA.'!H58:H1057),"HIGHEST VALUE","LOWEST VALUE") -> HIGHEST VALUE | S58: =IF(J58>0,"Profit","Loss") -> Profit | T58: =PROPER(B58) -> Rose Garcia | U58: =PROPER(C58) -> Table | V58: =YEAR(K58) -> 2025 | W58: =MONTH(L58) -> 3 | X58: =DAY(K58) -> 18 | Y58: =TEXT(K58,"MMM") -> Mar | Z58: =L58-K58 -> 8
A59: ORD0058 | B59: Christopher Richardson | C59: Desk | D59: Furniture | E59: North | F59: 13 | G59: 808.06 | H59: 10504.78 | I59: 6587.76 | J59: 3917.02 | K59: 45887 | L59: 45897 | M59: Diya | N59: 5 | O59: 11:10:00 | P59: 7.9 | Q59: =RIGHT(A59,"4") -> 0058 | R59: =IF('RETAIL SALES DATA.'!H59>AVERAGE('RETAIL SALES DATA.'!H59:H1058),"HIGHEST VALUE","LOWEST VALUE") -> LOWEST VALUE | S59: =IF(J59>0,"Profit","Loss") -> Profit | T59: =PROPER(B59) -> Christopher Richardson | U59: =PROPER(C59) -> Desk | V59: =YEAR(K59) -> 2025 | W59: =MONTH(L59) -> 8 | X59: =DAY(K59) -> 18 | Y59: =TEXT(K59,"MMM") -> Aug | Z59: =L59-K59 -> 10
A60: ORD0059 | B60: Larry Johnson | C60: Mouse | D60: Electronics | E60: East | F60: 17 | G60: 3010.68 | H60: 51181.56 | I60: 35293.48 | J60: 15888.08 | K60: 46120 | L60: 46130 | M60: Sneha | N60: 1 | O60: 11:20:00 | P60: 6.5 | Q60: =RIGHT(A60,"4") -> 0059 | R60: =IF('RETAIL SALES DATA.'!H60>AVERAGE('RETAIL SALES DATA.'!H60:H1059),"HIGHEST VALUE","LOWEST VALUE") -> HIGHEST VALUE | S60: =IF(J60>0,"Profit","Loss") -> Profit | T60: =PROPER(B60) -> Larry Johnson | U60: =PROPER(C60) -> Mouse | V60: =YEAR(K60) -> 2026 | W60: =MONTH(L60) -> 4 | X60: =DAY(K60) -> 8 | Y60: =TEXT(K60,"MMM") -> Apr | Z60: =L60-K60 -> 10
A61: ORD0060 | B61: Mark Yang | C61: Smartphone | D61: Electronics | E61: West | F61: 3 | G61: 2680.27 | H61: 8040.81 | I61: 6408.63 | J61: 1632.18 | K61: 46161 | L61: 46162 | M61: Anjali | N61: 5 | O61: 10:57:00 | P61: 8.9 | Q61: =RIGHT(A61,"4") -> 0060 | R61: =IF('RETAIL SALES DATA.'!H61>AVERAGE('RETAIL SALES DATA.'!H61:H1060),"HIGHEST VALUE","LOWEST VALUE") -> LOWEST VALUE | S61: =IF(J61>0,"Profit","Loss") -> Profit | T61: =PROPER(B61) -> Mark Yang | U61: =PROPER(C61) -> Smartphone | V61: =YEAR(K61) -> 2026 | W61: =MONTH(L61) -> 5 | X61: =DAY(K61) -> 19 | Y61: =TEXT(K61,"MMM") -> May | Z61: =L61-K61 -> 1
A62: ORD0061 | B62: Jill Garcia | C62: Monitor | D62: Electronics | E62: North | F62: 16 | G62: 2587.86 | H62: 41405.76 | I62: 30864.46 | J62: 10541.3 | K62: 45741 | L62: 45748 | M62: Sneha | N62: 4 | O62: 08:31:00 | P62: 6.2 | Q62: =RIGHT(A62,"4") -> 0061 | R62: =IF('RETAIL SALES DATA.'!H62>AVERAGE('RETAIL SALES DATA.'!H62:H1061),"HIGHEST VALUE","LOWEST VALUE") -> HIGHEST VALUE | S62: =IF(J62>0,"Profit","Loss") -> Profit | T62: =PROPER(B62) -> Jill Garcia | U62: =PROPER(C62) -> Monitor | V62: =YEAR(K62) -> 2025 | W62: =MONTH(L62) -> 4 | X62: =DAY(K62) -> 25 | Y62: =TEXT(K62,"MMM") -> Mar | Z62: =L62-K62 -> 7
A63: ORD0062 | B63: Anne Rodriguez | C63: Smartphone | D63: Electronics | E63: North | F63: 8 | G63: 1185.57 | H63: 9484.56 | I63: 5385.46 | J63: 4099.1 | K63: 46118 | L63: 46121 | M63: Akhil | N63: 2 | O63: 11:00:00 | P63: 8.2 | Q63: =RIGHT(A63,"4") -> 0062 | R63: =IF('RETAIL SALES DATA.'!H63>AVERAGE('RETAIL SALES DATA.'!H63:H1062),"HIGHEST VALUE","LOWEST VALUE") -> LOWEST VALUE | S63: =IF(J63>0,"Profit","Loss") -> Profit | T63: =PROPER(B63) -> Anne Rodriguez | U63: =PROPER(C63) -> Smartphone | V63: =YEAR(K63) -> 2026 | W63: =MONTH(L63) -> 4 | X63: =DAY(K63) -> 6 | Y63: =TEXT(K63,"MMM") -> Apr | Z63: =L63-K63 -> 3
A64: ORD0063 | B64: Christopher Daniels | C64: Cupboard | D64: Furniture | E64: West | F64: 9 | G64: 3551.24 | H64: 31961.16 | I64: 26905.37 | J64: 5055.79 | K64: 46002 | L64: 46004 | M64: Sneha | N64: 5 | O64: 11:36:00 | P64: 7.8 | Q64: =RIGHT(A64,"4") -> 0063 | R64: =IF('RETAIL SALES DATA.'!H64>AVERAGE('RETAIL SALES DATA.'!H64:H1063),"HIGHEST VALUE","LOWEST VALUE") -> HIGHEST VALUE | S64: =IF(J64>0,"Profit","Loss") -> Profit | T64: =PROPER(B64) -> Christopher Daniels | U64: =PROPER(C64) -> Cupboard | V64: =YEAR(K64) -> 2025 | W64: =MONTH(L64) -> 12 | X64: =DAY(K64) -> 11 | Y64: =TEXT(K64,"MMM") -> Dec | Z64: =L64-K64 -> 2
A65: ORD0064 | B65: Joshua Stevenson | C65: Marker | D65: Office Supplies | E65: West | F65: 15 | G65: 994.46 | H65: 14916.9 | I65: 11569.14 | J65: 3347.76 | K65: 46012 | L65: 46017 | M65: Nikhil | N65: 5 | O65: 10:24:00 | P65: 7.2 | Q65: =RIGHT(A65,"4") -> 0064 | R65: =IF('RETAIL SALES DATA.'!H65>AVERAGE('RETAIL SALES DATA.'!H65:H1064),"HIGHEST VALUE","LOWEST VALUE") -> LOWEST VALUE | S65: =IF(J65>0,"Profit","Loss") -> Profit | T65: =PROPER(B65) -> Joshua Stevenson | U65: =PROPER(C65) -> Marker | V65: =YEAR(K65) -> 2025 | W65: =MONTH(L65) -> 12 | X65: =DAY(K65) -> 21 | Y65: =TEXT(K65,"MMM") -> Dec | Z65: =L65-K65 -> 5
A66: ORD0065 | B66: Caleb Schneider | C66: Monitor | D66: Electronics | E66: North | F66: 6 | G66: 452.56 | H66: 2715.36 | I66: 1367.52 | J66: 1347.84 | K66: 45841 | L66: 45846 | M66: Anjali | N66: 4 | O66: 09:32:00 | P66: 10 | Q66: =RIGHT(A66,"4") -> 0065 | R66: =IF('RETAIL SALES DATA.'!H66>AVERAGE('RETAIL SALES DATA.'!H66:H1065),"HIGHEST VALUE","LOWEST VALUE") -> LOWEST VALUE | S66: =IF(J66>0,"Profit","Loss") -> Profit | T66: =PROPER(B66) -> Caleb Schneider | U66: =PROPER(C66) -> Monitor | V66: =YEAR(K66) -> 2025 | W66: =MONTH(L66) -> 7 | X66: =DAY(K66) -> 3 | Y66: =TEXT(K66,"MMM") -> Jul | Z66: =L66-K66 -> 5
... A1001: ORD1000 | B1001: Matthew Bradley | C1001: Cupboard | D1001: Furniture | E1001: West | F1001: 16 | G1001: 3752.49 | H1001: 60039.84 | I1001: 36366.23 | J1001: 23673.61 | K1001: 45821 | L1001: 45827 | M1001: Diya | N1001: 4 | O1001: 11:29:00 | P1001: 6.4 | Q1001: =RIGHT(A1001,"4") -> 1000 | R1001: =IF('RETAIL SALES DATA.'!H1001>AVERAGE('RETAIL SALES DATA.'!H1001:H2000),"HIGHEST VALUE","LOWEST VALUE") -> LOWEST VALUE | S1001: =IF(J1001>0,"Profit","Loss") -> Profit | T1001: =PROPER(B1001) -> Matthew Bradley | U1001: =PROPER(C1001) -> Cupboard | V1001: =YEAR(K1001) -> 2025 | W1001: =MONTH(L1001) -> 6 | X1001: =DAY(K1001) -> 13 | Y1001: =TEXT(K1001,"MMM") -> Jun | Z1001: =L1001-K1001 -> 6
U1094: ZZ

Sheet Sheet1
A1: BEST SELLING PRODUCT | B1: QUANTITY | C1: PRODUCT
B2: =SUMIFS('RETAIL SALES DATA.'!F2:F1001,'RETAIL SALES DATA.'!C2:C1001,C2) -> 633 | C2: {=_xlfn.UNIQUE('RETAIL SALES DATA.'!C2:C1001)} -> Pen
B3: =SUMIFS('RETAIL SALES DATA.'!F3:F1002,'RETAIL SALES DATA.'!C3:C1002,C3) -> 859 | C3: Desk | D3: BEST SELLING
B4: =SUMIFS('RETAIL SALES DATA.'!F4:F1003,'RETAIL SALES DATA.'!C4:C1003,C4) -> 590 | C4: Marker | D4: LEAST SELLING | I4: Total Sales | J4: =SUM('RETAIL SALES DATA.'!H2:H1001) -> 26471144
B5: =SUMIFS('RETAIL SALES DATA.'!F5:F1004,'RETAIL SALES DATA.'!C5:C1004,C5) -> 691 | C5: Laptop | I5: Total profit | J5: =SUM('RETAIL SALES DATA.'!J2:J1001) -> 8204131.4
B6: =SUMIFS('RETAIL SALES DATA.'!F6:F1005,'RETAIL SALES DATA.'!C6:C1005,C6) -> 747 | C6: Mouse | I6: Total Quantitysold | J6: =SUM('RETAIL SALES DATA.'!F2:F1001) -> 10506
B7: =SUMIFS('RETAIL SALES DATA.'!F7:F1006,'RETAIL SALES DATA.'!C7:C1006,C7) -> 635 | C7: Notebook
B8: =SUMIFS('RETAIL SALES DATA.'!F8:F1007,'RETAIL SALES DATA.'!C8:C1007,C8) -> 688 | C8: Table
B9: =SUMIFS('RETAIL SALES DATA.'!F9:F1008,'RETAIL SALES DATA.'!C9:C1008,C9) -> 768 | C9: Chair
B10: =SUMIFS('RETAIL SALES DATA.'!F10:F1009,'RETAIL SALES DATA.'!C10:C1009,C10) -> 672 | C10: Cupboard
B11: =SUMIFS('RETAIL SALES DATA.'!F11:F1010,'RETAIL SALES DATA.'!C11:C1010,C11) -> 832 | C11: Printer
B12: =SUMIFS('RETAIL SALES DATA.'!F12:F1011,'RETAIL SALES DATA.'!C12:C1011,C12) -> 693 | C12: Sofa
B13: =SUMIFS('RETAIL SALES DATA.'!F13:F1012,'RETAIL SALES DATA.'!C13:C1012,C13) -> 767 | C13: File
B14: =SUMIFS('RETAIL SALES DATA.'!F14:F1013,'RETAIL SALES DATA.'!C14:C1013,C14) -> 671 | C14: Keyboard
B15: =SUMIFS('RETAIL SALES DATA.'!F15:F1014,'RETAIL SALES DATA.'!C15:C1014,C15) -> 657 | C15: Monitor
B16: =SUMIFS('RETAIL SALES DATA.'!F16:F1015,'RETAIL SALES DATA.'!C16:C1015,C16) -> 603 | C16: Smartphone
A18: SALES&PROFIT
B19: CATEGORY | C19: HIGH | D19: LOW
B20: SALES | C20: =MAX('RETAIL SALES DATA.'!H2:H1001) -> 96471.6 | D20: =MIN('RETAIL SALES DATA.'!H2:H1001) -> 84.04
B21: PROFIT | C21: =MAX('RETAIL SALES DATA.'!J2:J1001) -> 41219.44 | D21: =MIN('RETAIL SALES DATA.'!J2:J1001) -> 10.48
A24: AVDERAGE SALES AND PROFIT
B27: AVERAGE PROFIT | C27: AVERAGE SALES
B28: =AVERAGE('RETAIL SALES DATA.'!J2:J1001) -> 8204.1314 | C28: =AVERAGE('RETAIL SALES DATA.'!H2:H1001) -> 26471.144
A30: REGION GENERATED HIGHEST VALUE
B33: {=_xlfn.UNIQUE('RETAIL SALES DATA.'!E2:E1001)} -> South | C33: =SUMIF('RETAIL SALES DATA.'!E2:E1001,B33,'RETAIL SALES DATA.'!H2:H1001) -> 5968196.4
B34: North | C34: =SUMIF('RETAIL SALES DATA.'!E3:E1002,B34,'RETAIL SALES DATA.'!H3:H1002) -> 6653980.9
B35: West | C35: =SUMIF('RETAIL SALES DATA.'!E4:E1003,B35,'RETAIL SALES DATA.'!H4:H1003) -> 7688782.6 | D35: GENERATED HIGHEST VALUE
B36: East | C36: =SUMIF('RETAIL SALES DATA.'!E5:E1004,B36,'RETAIL SALES DATA.'!H5:H1004) -> 6160183.7
A38: NUMBERS OF ORDERS FROM EACH REGION
B41: {=_xlfn.UNIQUE('RETAIL SALES DATA.'!E2:E1001)} -> South | C41: =COUNTIF('RETAIL SALES DATA.'!E2:E1001,B41) -> 230
B42: North | C42: =COUNTIF('RETAIL SALES DATA.'!E3:E1002,B42) -> 251
B43: West | C43: =COUNTIF('RETAIL SALES DATA.'!E4:E1003,B43) -> 282
B44: East | C44: =COUNTIF('RETAIL SALES DATA.'!E5:E1004,B44) -> 237
A47: SALES FOR EACH CATEGORY
B48: {=_xlfn.UNIQUE('RETAIL SALES DATA.'!E17:E1016)} -> West | C48: =SUMIF('RETAIL SALES DATA.'!E17:E1016,B48,'RETAIL SALES DATA.'!H17:H1016) -> 7566871.8
B49: North | C49: =SUMIF('RETAIL SALES DATA.'!E18:E1017,B49,'RETAIL SALES DATA.'!H18:H1017) -> 6582015.8
B50: South | C50: =SUMIF('RETAIL SALES DATA.'!E19:E1018,B50,'RETAIL SALES DATA.'!H19:H1018) -> 5909004.6
B51: East | C51: =SUMIF('RETAIL SALES DATA.'!E20:E1019,B51,'RETAIL SALES DATA.'!H20:H1019) -> 6062618.1
B52: 0
A53: CLASSIFY TRANSACTION
B54: Profit | C54: =COUNTIF('RETAIL SALES DATA.'!S2:S1001,'RETAIL SALES DATA.'!S978) -> 1000
B55: Loss | C55: =COUNTIF('RETAIL SALES DATA.'!S974:S1001,"Loss") -> 0
A57: HIGH VALUE AND LOW VALUE
B58: TOTAL HIGHEST VALUE ORDERS | C58: =COUNTIF('RETAIL SALES DATA.'!R2:R1001,'RETAIL SALES DATA.'!R980) -> 405 | D58: MORE THAN AVERAGE
B59: TOTAL LOWESTR VALUE ORDERS | C59: =COUNTIF('RETAIL SALES DATA.'!R1:R1001,'RETAIL SALES DATA.'!R2) -> 595 | D59: LESS THAN AVERAGE
A62: USEFULL INFORMATION COLLECTED
B63: TOTAL ORDERS | C63: 1000
B65: YEARLY SALES | C65: {=_xlfn.UNIQUE('RETAIL SALES DATA.'!V2:V1001)} -> 2025 | D65: =SUMIF('RETAIL SALES DATA.'!V2:V1001,'RETAIL SALES DATA.'!V965,'RETAIL SALES DATA.'!H2:H1001) -> 13413606
C66: 2026 | D66: =SUMIF('RETAIL SALES DATA.'!V3:V1002,'RETAIL SALES DATA.'!V966,'RETAIL SALES DATA.'!H3:H1002) -> 8340960.3
C67: 2024 | D67: =SUMIF('RETAIL SALES DATA.'!V4:V1003,'RETAIL SALES DATA.'!V967,'RETAIL SALES DATA.'!H4:H1003) -> 4690875.8
B70: MONTHLY SALES
C72: MONTH | D72: 2025 | E72: 2024 | F72: 2026
C73: Jan | D73: 931394.12 | E73: 0 | F73: 1122389.7
C74: Feb | D74: 1188601.5 | E74: 0 | F74: 855184.88
C75: Mar | D75: 1343369.7 | E75: 1343369.7 | F75: 0
C76: Apr | D76: 898947.59 | E76: 1380237 | F76: 898947.59
C77: May | D77: 530012.66 | E77: 1003309.7 | F77: 530012.66
C78: Jun | D78: 1180005.8 | E78: 0 | F78: 1180005.8
C79: Jul | D79: 1051466.1 | E79: 1051466.1 | F79: 0
C80: Aug | D80: 1122773.1 | E80: 1122773.1 | F80: 1435955.9
C81: Sep | D81: 1045399.3 | E81: 1045399.3 | F81: 1045399.3
C82: Oct | D82: 0 | E82: 1137093.4 | F82: 1301211.4
C83: Nov | D83: 1086755.5 | E83: 0 | F83: 1086755.5
C84: Dec | D84: 1027155.3 | E84: 1027155.3 | F84: 1027155.3
B87: YEARLY SALES
C89: YEAR
C90: 2024 | D90: 8340960.3
C91: 2025 | D91: 13413606
C92: 2026 | D92: 4716577.1
B97: DELIVERY
C98: MAXIMUM DELIVERY DAYS | D98: =MAX(Table13[DELIVERY DATE]) -> 10
C99: MINIMUM DELIVERY DAYS | D99: =MIN(Table13[DELIVERY DATE]) -> 1
